pizza_app/__init__.py
pizza_app/cli.py
pizza_app/main.py
pizza_app/my_lib.py
pizza_app/pizza.kv
pizza_app/secure_password.py
pizza_app/assets/databases/login.sql
pizza_app/assets/databases/menu.sql
pizza_app/assets/databases/orders.sql
pizza_app/assets/images/coke.png
pizza_app/assets/images/fries.png
pizza_app/assets/images/logo.png
pizza_app/assets/images/mushroom.png
pizza_app/assets/images/pizza.png
pizza_app/assets/images/pizza_background.png
pizza_ordering_app-1.0.6.dist-info/licenses/LICENSE
pizza_ordering_app-1.0.6.dist-info/METADATA
pizza_ordering_app-1.0.6.dist-info/WHEEL
pizza_ordering_app-1.0.6.dist-info/entry_points.txt
pizza_ordering_app-1.0.6.dist-info/top_level.txt
pizza_ordering_app-1.0.6.dist-info/RECORD
