Metadata-Version: 2.4
Name: pizza-ordering-app
Version: 1.0.6
Summary: A beautiful pizza ordering application built with KivyMD
Home-page: https://github.com/al1kss/pizza-app
Author: Alikhan Abdykaimov
Author-email: Alikhan Abdykaimov <2026.alikhan.abdykaimov@uwcisak.jp>
License: MIT
Project-URL: Homepage, https://github.com/al1kss/pizza-app
Project-URL: Bug Reports, https://github.com/al1kss/pizza-app/issues
Project-URL: Source, https://github.com/al1kss/pizza-app/
Keywords: kivymd,pizza,ordering,app,restaurant,gui,mobile
Classifier: Development Status :: 4 - Beta
Classifier: Intended Audience :: End Users/Desktop
Classifier: License :: OSI Approved :: MIT License
Classifier: Operating System :: OS Independent
Classifier: Programming Language :: Python :: 3
Classifier: Programming Language :: Python :: 3.7
Classifier: Programming Language :: Python :: 3.8
Classifier: Programming Language :: Python :: 3.9
Classifier: Programming Language :: Python :: 3.10
Classifier: Programming Language :: Python :: 3.11
Classifier: Topic :: Software Development :: User Interfaces
Classifier: Topic :: Games/Entertainment
Requires-Python: >=3.7
License-File: LICENSE
Requires-Dist: kivymd>=1.2.0
Requires-Dist: kivy>=2.2.0
Requires-Dist: passlib>=1.7.4
Dynamic: author
Dynamic: home-page
Dynamic: license-file
Dynamic: requires-python
